bin/libPCGPack.a
bin/FiniteVolume_x64
bin/libExpressionParser.a
bin/libsundials_ida.a
bin/libsundials_nvecserial.a
bin/libvcellziputils.a
bin/libqhull.a
bin/libvcellmessaging.a
bin/libsundials_lib.a
bin/libsundials_cvode.a
pyvcell_fvsolver-0.1.0.dist-info/RECORD
pyvcell_fvsolver-0.1.0.dist-info/WHEEL
pyvcell_fvsolver-0.1.0.dist-info/METADATA
pyvcell_fvsolver-0.1.0.dist-info/licenses/LICENSE
pyvcell_fvsolver/__init__.py
pyvcell_fvsolver/_core.cpython-310-darwin.so
pyvcell_fvsolver/.dylibs/libgfortran.5.dylib
pyvcell_fvsolver/.dylibs/libsz.2.0.1.dylib
pyvcell_fvsolver/.dylibs/libzip.5.5.dylib
pyvcell_fvsolver/.dylibs/libzstd.1.5.6.dylib
pyvcell_fvsolver/.dylibs/liblzma.5.dylib
pyvcell_fvsolver/.dylibs/libquadmath.0.dylib
pyvcell_fvsolver/.dylibs/libgcc_s.1.1.dylib
