Metadata-Version: 2.1
Name: pyvcell_fvsolver
Version: 0.1.0
Summary: Virtual Cell Finite Volume PDE solver
Author-Email: Jim Schaff <schaff@uchc.edu>
Classifier: Development Status :: 4 - Beta
Classifier: License :: OSI Approved :: MIT License
Classifier: Programming Language :: Python :: 3 :: Only
Classifier: Programming Language :: Python :: 3.9
Classifier: Programming Language :: Python :: 3.10
Classifier: Programming Language :: Python :: 3.11
Classifier: Programming Language :: Python :: 3.12
Requires-Python: >=3.9
Provides-Extra: test
Requires-Dist: pytest; extra == "test"
